<?xml version="1.0" encoding="UTF-8"?>
<objects serializationModel="Studio.02.01.00">
	<object class="EffectPreset" id="{35541620-b301-44d3-bd39-5ad1f1aa67d6}">
		<property name="name">
			<value>Effect Chain</value>
		</property>
		<relationship name="folder">
			<destination>{0c0522aa-61d6-42ce-a6a6-c81f8ac42b12}</destination>
		</relationship>
		<relationship name="effect">
			<destination>{327b4fa3-706a-4744-8a00-ccffb0519c45}</destination>
		</relationship>
	</object>
	<object class="EffectChain" id="{327b4fa3-706a-4744-8a00-ccffb0519c45}" />
</objects>
