<?xml version="1.0" encoding="UTF-8"?>
<objects serializationModel="Studio.02.01.00">
	<object class="AudioFile" id="{5baf7ad4-eff0-4c0c-8a90-e7cb23801847}">
		<property name="assetPath">
			<value>35213__abyssmal__slashkut.wav</value>
		</property>
		<property name="frequencyInKHz">
			<value>44.0999985</value>
		</property>
		<property name="channelCount">
			<value>2</value>
		</property>
		<property name="length">
			<value>0.49170068027210884</value>
		</property>
		<relationship name="masterAssetFolder">
			<destination>{a44840a7-1751-4e1d-83bb-fef9de00a311}</destination>
		</relationship>
	</object>
</objects>
